tasmanian/__init__.py
tasmanian/manuscript.txt
tasmanian/tasmanian_script.py
tasmanian/galaxy_wrapper/tasmanian_galaxy.py
tasmanian/scripts/collect_data.py
tasmanian/scripts/count_CpG_GC_repeat.py
tasmanian/scripts/hist.py
tasmanian/test_suite/colordiff.py
tasmanian/test_suite/plotit.py
tasmanian/tests/intersections_test.py
tasmanian/tests/tasmanian_test.py
tasmanian/utils/__init__.py
tasmanian/utils/constants.py
tasmanian/utils/intersections.py
tasmanian/utils/plot.py
tasmanian/utils/sam_reads.py
tasmanian/utils/utils.py
tasmanian_mismatch-1.0.9.data/scripts/run_intersections
tasmanian_mismatch-1.0.9.data/scripts/run_tasmanian
tasmanian_mismatch-1.0.9.dist-info/licenses/LICENCE.txt
tasmanian_mismatch-1.0.9.dist-info/METADATA
tasmanian_mismatch-1.0.9.dist-info/WHEEL
tasmanian_mismatch-1.0.9.dist-info/top_level.txt
tasmanian_mismatch-1.0.9.dist-info/RECORD
