Metadata-Version: 2.4
Name: tasmanian-mismatch
Version: 1.0.9
Summary: Tasmanian tool to analyze mismatches at read and position in high throughput sequencing data
Home-page: https://github.com/nebiolabs/tasmanian-mismatch
Author: Ariel Erijman and Brad Langhorst
Author-email: Ariel Erijman <aerijman@neb.com>, Brad Langhorst <blanghorst@neb.com>
License: GNU
Project-URL: Homepage, https://github.com/nebiolabs/tasmanian-mismatch
Project-URL: Repository, https://github.com/nebiolabs/tasmanian-mismatch
Project-URL: Issues, https://github.com/nebiolabs/tasmanian-mismatch/issues
Keywords: sequencing,bioinformatics,mismatch,analysis
Classifier: Development Status :: 5 - Production/Stable
Classifier: Intended Audience :: Science/Research
Classifier: License :: OSI Approved :: GNU General Public License (GPL)
Classifier: Programming Language :: Python :: 3
Classifier: Programming Language :: Python :: 3.10
Classifier: Programming Language :: Python :: 3.11
Classifier: Programming Language :: Python :: 3.12
Classifier: Topic :: Scientific/Engineering :: Bio-Informatics
Requires-Python: >=3.10,<3.13
License-File: LICENCE.txt
Requires-Dist: numpy
Requires-Dist: pandas
Requires-Dist: scipy
Requires-Dist: plotly
Dynamic: author
Dynamic: home-page
Dynamic: license-file
Dynamic: requires-python
